hdwallet/__init__.py
hdwallet/exceptions.py
hdwallet/keys.py
hdwallet/typing.py
hdwallet/utils.py
py_hdwallet-0.1.0a1.dist-info/LICENSE
py_hdwallet-0.1.0a1.dist-info/METADATA
py_hdwallet-0.1.0a1.dist-info/WHEEL
py_hdwallet-0.1.0a1.dist-info/top_level.txt
py_hdwallet-0.1.0a1.dist-info/RECORD
