Metadata-Version: 2.1
Name: py-hdwallet
Version: 0.1.0a1
Summary: py-hdwallet: HD wallet generator.
Home-page: https://github.com/ethereum/py-hdwallet
Author: The Ethereum Foundation
Author-email: snakecharmers@ethereum.org
License: MIT
Keywords: ethereum
Platform: UNKNOWN
Classifier: Development Status :: 3 - Alpha
Classifier: Intended Audience :: Developers
Classifier: License :: OSI Approved :: MIT License
Classifier: Natural Language :: English
Classifier: Programming Language :: Python :: 3
Classifier: Programming Language :: Python :: 3.6
Classifier: Programming Language :: Python :: 3.7
Classifier: Programming Language :: Python :: Implementation :: PyPy
Requires-Python: >=3.6, <4
Requires-Dist: ecdsa (<0.14.0,>=0.13.2)
Requires-Dist: base58 (<1.1.0,>=1.0.3)
Provides-Extra: dev
Requires-Dist: bumpversion (<1,>=0.5.3) ; extra == 'dev'
Requires-Dist: pytest-watch (<5,>=4.1.0) ; extra == 'dev'
Requires-Dist: wheel ; extra == 'dev'
Requires-Dist: twine ; extra == 'dev'
Requires-Dist: ipython ; extra == 'dev'
Requires-Dist: pytest (==5.0.1) ; extra == 'dev'
Requires-Dist: pytest-xdist ; extra == 'dev'
Requires-Dist: tox (<3,>=2.9.1) ; extra == 'dev'
Requires-Dist: flake8 (==3.4.1) ; extra == 'dev'
Requires-Dist: isort (<5,>=4.2.15) ; extra == 'dev'
Requires-Dist: mypy (==0.701) ; extra == 'dev'
Requires-Dist: pydocstyle (<4,>=3.0.0) ; extra == 'dev'
Requires-Dist: Sphinx (<2,>=1.6.5) ; extra == 'dev'
Requires-Dist: sphinx-rtd-theme (>=0.1.9) ; extra == 'dev'
Provides-Extra: doc
Requires-Dist: Sphinx (<2,>=1.6.5) ; extra == 'doc'
Requires-Dist: sphinx-rtd-theme (>=0.1.9) ; extra == 'doc'
Provides-Extra: lint
Requires-Dist: flake8 (==3.4.1) ; extra == 'lint'
Requires-Dist: isort (<5,>=4.2.15) ; extra == 'lint'
Requires-Dist: mypy (==0.701) ; extra == 'lint'
Requires-Dist: pydocstyle (<4,>=3.0.0) ; extra == 'lint'
Provides-Extra: test
Requires-Dist: pytest (==5.0.1) ; extra == 'test'
Requires-Dist: pytest-xdist ; extra == 'test'
Requires-Dist: tox (<3,>=2.9.1) ; extra == 'test'
